{
  "school_code": "DCL",
  "school_name": "Trường Đại Học Cửu Long",
  "tables": [
    {
      "table_title": "Điểm thi THPT năm 2024",
      "headers": [
        "Tên ngành",
        "Tổ hợp môn",
        "Điểm chuẩn",
        "Ghi chú"
      ],
      "data": [
        {
          "Tên ngành": "Thiết kế đồ họa",
          "Tổ hợp môn": "A00; A01; C04; D01",
          "Điểm chuẩn": "15",
          "Ghi chú": ""
        },
        {
          "Tên ngành": "Tiếng Việt & Văn hóa Việt Nam",
          "Tổ hợp môn": "C00; D01; D14; D15",
          "Điểm chuẩn": "15",
          "Ghi chú": ""
        },
        {
          "Tên ngành": "Ngôn ngữ Anh",
          "Tổ hợp môn": "A01; D01; D14; D15",
          "Điểm chuẩn": "15",
          "Ghi chú": ""
        },
        {
          "Tên ngành": "Đông phương học",
          "Tổ hợp môn": "A01; C00; D01; D14",
          "Điểm chuẩn": "15",
          "Ghi chú": ""
        },
        {
          "Tên ngành": "Quản trị kinh doanh",
          "Tổ hợp môn": "A00; A01; D01; C04",
          "Điểm chuẩn": "15",
          "Ghi chú": ""
        },
        {
          "Tên ngành": "Kinh doanh thương mại",
          "Tổ hợp môn": "A00; A01; D01; C04",
          "Điểm chuẩn": "15",
          "Ghi chú": ""
        },
        {
          "Tên ngành": "Marketing",
          "Tổ hợp môn": "A00; A01; D01; C04",
          "Điểm chuẩn": "15",
          "Ghi chú": ""
        },
        {
          "Tên ngành": "Tài chính - Ngân hàng",
          "Tổ hợp môn": "A00; A01; D01; C04",
          "Điểm chuẩn": "15",
          "Ghi chú": ""
        },
        {
          "Tên ngành": "Kế toán",
          "Tổ hợp môn": "A00; A01; D01; C04",
          "Điểm chuẩn": "15",
          "Ghi chú": ""
        },
        {
          "Tên ngành": "Luật",
          "Tổ hợp môn": "A00; A01; C00; D01",
          "Điểm chuẩn": "15",
          "Ghi chú": ""
        },
        {
          "Tên ngành": "Luật kinh tế",
          "Tổ hợp môn": "A00; A01; C00; D01",
          "Điểm chuẩn": "15",
          "Ghi chú": ""
        },
        {
          "Tên ngành": "Công nghệ thông tin",
          "Tổ hợp môn": "A00; A01; D01; D07",
          "Điểm chuẩn": "15",
          "Ghi chú": ""
        },
        {
          "Tên ngành": "Công nghệ kỹ thuật công trình xây dựng (Thiết kế kiến trúc xây dựng)",
          "Tổ hợp môn": "A00; A01; D01; C01",
          "Điểm chuẩn": "15",
          "Ghi chú": ""
        },
        {
          "Tên ngành": "Công nghệ kỹ thuật cơ khí",
          "Tổ hợp môn": "A00; A01; D01; C01",
          "Điểm chuẩn": "15",
          "Ghi chú": ""
        },
        {
          "Tên ngành": "Công nghệ kỹ thuật ô tô",
          "Tổ hợp môn": "A00; A01; D01; C01",
          "Điểm chuẩn": "15",
          "Ghi chú": ""
        },
        {
          "Tên ngành": "Công nghệ kỹ thuật điện, điện tử",
          "Tổ hợp môn": "A00; A01; D01; C01",
          "Điểm chuẩn": "15",
          "Ghi chú": ""
        },
        {
          "Tên ngành": "Kỹ thuật y sinh",
          "Tổ hợp môn": "A00; A01; D01; C01",
          "Điểm chuẩn": "15",
          "Ghi chú": ""
        },
        {
          "Tên ngành": "Công nghệ thực phẩm",
          "Tổ hợp môn": "A00; A01; B00; C01",
          "Điểm chuẩn": "15",
          "Ghi chú": ""
        },
        {
          "Tên ngành": "Kỹ thuật xây dựng công trình giao thông",
          "Tổ hợp môn": "A00; A01; D01; C01",
          "Điểm chuẩn": "15",
          "Ghi chú": ""
        },
        {
          "Tên ngành": "Nông học",
          "Tổ hợp môn": "A00; A01; B00; B03",
          "Điểm chuẩn": "15",
          "Ghi chú": ""
        },
        {
          "Tên ngành": "Bảo vệ thực vật",
          "Tổ hợp môn": "A00; A01; B00; B03",
          "Điểm chuẩn": "15",
          "Ghi chú": ""
        },
        {
          "Tên ngành": "Nuôi trồng thủy sản",
          "Tổ hợp môn": "A00; A01; B00; B03",
          "Điểm chuẩn": "15",
          "Ghi chú": ""
        },
        {
          "Tên ngành": "Thú y",
          "Tổ hợp môn": "A00; A01; B00; B03",
          "Điểm chuẩn": "15",
          "Ghi chú": ""
        },
        {
          "Tên ngành": "Y khoa",
          "Tổ hợp môn": "A00; A02; B00; D07",
          "Điểm chuẩn": "22.5",
          "Ghi chú": ""
        },
        {
          "Tên ngành": "Dược học",
          "Tổ hợp môn": "A00; B00; C08; D07",
          "Điểm chuẩn": "21",
          "Ghi chú": ""
        },
        {
          "Tên ngành": "Điều dưỡng",
          "Tổ hợp môn": "A02; B00; B03; D08",
          "Điểm chuẩn": "19",
          "Ghi chú": ""
        },
        {
          "Tên ngành": "Hộ sinh",
          "Tổ hợp môn": "A02; B00; B03; D07",
          "Điểm chuẩn": "19",
          "Ghi chú": ""
        },
        {
          "Tên ngành": "Kỹ thuật xét nghiệm y học",
          "Tổ hợp môn": "A00; B00; B03; D07",
          "Điểm chuẩn": "19",
          "Ghi chú": ""
        },
        {
          "Tên ngành": "Kỹ thuật hình ảnh y học",
          "Tổ hợp môn": "A00; A02; B00; D07",
          "Điểm chuẩn": "19",
          "Ghi chú": ""
        },
        {
          "Tên ngành": "Công tác xã hội",
          "Tổ hợp môn": "A01; C00; C01; D01",
          "Điểm chuẩn": "15",
          "Ghi chú": ""
        },
        {
          "Tên ngành": "Quản trị dịch vụ du lịch & lữ hành",
          "Tổ hợp môn": "A00; A01; C00; D01",
          "Điểm chuẩn": "15",
          "Ghi chú": ""
        }
      ],
      "row_count": 31
    },
    {
      "table_title": "Điểm học bạ năm 2024",
      "headers": [
        "Tên ngành",
        "Tổ hợp môn",
        "Điểm chuẩn",
        "Ghi chú"
      ],
      "data": [
        {
          "Tên ngành": "Thiết kế đồ họa",
          "Tổ hợp môn": "A00; A01; C04; D01",
          "Điểm chuẩn": "6",
          "Ghi chú": ""
        },
        {
          "Tên ngành": "Tiếng Việt & Văn hóa Việt Nam",
          "Tổ hợp môn": "C00; D01; D14; D15",
          "Điểm chuẩn": "6",
          "Ghi chú": ""
        },
        {
          "Tên ngành": "Ngôn ngữ Anh",
          "Tổ hợp môn": "A01; D01; D14; D15",
          "Điểm chuẩn": "6",
          "Ghi chú": ""
        },
        {
          "Tên ngành": "Đông phương học",
          "Tổ hợp môn": "A01; C00; D01; D14",
          "Điểm chuẩn": "6",
          "Ghi chú": ""
        },
        {
          "Tên ngành": "Quản trị kinh doanh",
          "Tổ hợp môn": "A00; A01; D01; C04",
          "Điểm chuẩn": "6",
          "Ghi chú": ""
        },
        {
          "Tên ngành": "Kinh doanh thương mại",
          "Tổ hợp môn": "A00; A01; D01; C04",
          "Điểm chuẩn": "6",
          "Ghi chú": ""
        },
        {
          "Tên ngành": "Marketing",
          "Tổ hợp môn": "A00; A01; D01; C04",
          "Điểm chuẩn": "6",
          "Ghi chú": ""
        },
        {
          "Tên ngành": "Tài chính - Ngân hàng",
          "Tổ hợp môn": "A00; A01; D01; C04",
          "Điểm chuẩn": "6",
          "Ghi chú": ""
        },
        {
          "Tên ngành": "Kế toán",
          "Tổ hợp môn": "A00; A01; D01; C04",
          "Điểm chuẩn": "6",
          "Ghi chú": ""
        },
        {
          "Tên ngành": "Luật",
          "Tổ hợp môn": "A00; A01; C00; D01",
          "Điểm chuẩn": "6",
          "Ghi chú": ""
        },
        {
          "Tên ngành": "Luật kinh tế",
          "Tổ hợp môn": "A00; A01; C00; D01",
          "Điểm chuẩn": "6",
          "Ghi chú": ""
        },
        {
          "Tên ngành": "Công nghệ thông tin",
          "Tổ hợp môn": "A00; A01; D01; D07",
          "Điểm chuẩn": "6",
          "Ghi chú": ""
        },
        {
          "Tên ngành": "Công nghệ kỹ thuật công trình xây dựng (Thiết kế kiến trúc xây dựng)",
          "Tổ hợp môn": "A00; A01; D01; C01",
          "Điểm chuẩn": "6",
          "Ghi chú": ""
        },
        {
          "Tên ngành": "Công nghệ kỹ thuật cơ khí",
          "Tổ hợp môn": "A00; A01; D01; C01",
          "Điểm chuẩn": "6",
          "Ghi chú": ""
        },
        {
          "Tên ngành": "Công nghệ kỹ thuật ô tô",
          "Tổ hợp môn": "A00; A01; D01; C01",
          "Điểm chuẩn": "6",
          "Ghi chú": ""
        },
        {
          "Tên ngành": "Công nghệ kỹ thuật điện, điện tử",
          "Tổ hợp môn": "A00; A01; D01; C01",
          "Điểm chuẩn": "6",
          "Ghi chú": ""
        },
        {
          "Tên ngành": "Kỹ thuật y sinh",
          "Tổ hợp môn": "A00; A01; D01; C01",
          "Điểm chuẩn": "6",
          "Ghi chú": ""
        },
        {
          "Tên ngành": "Công nghệ thực phẩm",
          "Tổ hợp môn": "A00; A01; B00; C01",
          "Điểm chuẩn": "6",
          "Ghi chú": ""
        },
        {
          "Tên ngành": "Kỹ thuật xây dựng công trình giao thông",
          "Tổ hợp môn": "A00; A01; D01; C01",
          "Điểm chuẩn": "6",
          "Ghi chú": ""
        },
        {
          "Tên ngành": "Nông học",
          "Tổ hợp môn": "A00; A01; B00; B03",
          "Điểm chuẩn": "6",
          "Ghi chú": ""
        },
        {
          "Tên ngành": "Bảo vệ thực vật",
          "Tổ hợp môn": "A00; A01; B00; B03",
          "Điểm chuẩn": "6",
          "Ghi chú": ""
        },
        {
          "Tên ngành": "Nuôi trồng thủy sản",
          "Tổ hợp môn": "A00; A01; B00; B03",
          "Điểm chuẩn": "6",
          "Ghi chú": ""
        },
        {
          "Tên ngành": "Thú y",
          "Tổ hợp môn": "A00; A01; B00; B03",
          "Điểm chuẩn": "6",
          "Ghi chú": ""
        },
        {
          "Tên ngành": "Dược học",
          "Tổ hợp môn": "A00; B00; C08; D07",
          "Điểm chuẩn": "8",
          "Ghi chú": "HL năm lớp 12 loại Giỏi hoặc ĐXTN THPT từ 8.0 trở lên"
        },
        {
          "Tên ngành": "Điều dưỡng",
          "Tổ hợp môn": "A02; B00; B03; D08",
          "Điểm chuẩn": "6.5",
          "Ghi chú": "HL năm lớp 12 đạt Khá trở lên hoặc ĐXTN THPT từ 6.5 trở lên."
        },
        {
          "Tên ngành": "Hộ sinh",
          "Tổ hợp môn": "A02; B00; B03; D07",
          "Điểm chuẩn": "6.5",
          "Ghi chú": "HL năm lớp 12 đạt Khá trở lên hoặc ĐXTN THPT từ 6.5 trở lên."
        },
        {
          "Tên ngành": "Kỹ thuật xét nghiệm y học",
          "Tổ hợp môn": "A00; B00; B03; D07",
          "Điểm chuẩn": "6.5",
          "Ghi chú": "HL năm lớp 12 đạt Khá trở lên hoặc ĐXTN THPT từ 6.5 trở lên."
        },
        {
          "Tên ngành": "Kỹ thuật hình ảnh y học",
          "Tổ hợp môn": "A00; A02; B00; D07",
          "Điểm chuẩn": "6.5",
          "Ghi chú": "HL năm lớp 12 đạt Khá trở lên hoặc ĐXTN THPT từ 6.5 trở lên."
        },
        {
          "Tên ngành": "Công tác xã hội",
          "Tổ hợp môn": "A01; C00; C01; D01",
          "Điểm chuẩn": "6",
          "Ghi chú": ""
        },
        {
          "Tên ngành": "Quản trị dịch vụ du lịch & lữ hành",
          "Tổ hợp môn": "A00; A01; C00; D01",
          "Điểm chuẩn": "6",
          "Ghi chú": ""
        }
      ],
      "row_count": 30
    }
  ],
  "table_count": 2,
  "crawled_at": "2025-07-18T23:28:26.995624",
  "source_url": "https://diemthi.tuyensinh247.com/diem-chuan/dai-hoc-cuu-long-DCL.html"
}