{
  "school_code": "DDT",
  "school_name": "Đại Học Duy Tân",
  "tables": [
    {
      "table_title": "Điểm thi THPT năm 2024",
      "headers": [
        "Tên ngành",
        "Tổ hợp môn",
        "Điểm chuẩn",
        "Ghi chú"
      ],
      "data": [
        {
          "Tên ngành": "Thiết kế đồ họa",
          "Tổ hợp môn": "A00; A16; V01; D01",
          "Điểm chuẩn": "16",
          "Ghi chú": ""
        },
        {
          "Tên ngành": "Thiết kế thời trang",
          "Tổ hợp môn": "A00; A16; V01; D01",
          "Điểm chuẩn": "16",
          "Ghi chú": ""
        },
        {
          "Tên ngành": "Ngôn ngữ Anh",
          "Tổ hợp môn": "D01; D14; D15; D72",
          "Điểm chuẩn": "16",
          "Ghi chú": ""
        },
        {
          "Tên ngành": "Ngôn ngữ Trung Quốc",
          "Tổ hợp môn": "D01; D14; D15; D72",
          "Điểm chuẩn": "16",
          "Ghi chú": ""
        },
        {
          "Tên ngành": "Ngôn ngữ Nhật",
          "Tổ hợp môn": "A01; D01; D14; D15",
          "Điểm chuẩn": "16",
          "Ghi chú": ""
        },
        {
          "Tên ngành": "Ngôn ngữ Hàn Quốc",
          "Tổ hợp môn": "D01; D13; D09; D10",
          "Điểm chuẩn": "16",
          "Ghi chú": ""
        },
        {
          "Tên ngành": "Văn học",
          "Tổ hợp môn": "C00; C15; D01; C04",
          "Điểm chuẩn": "16",
          "Ghi chú": ""
        },
        {
          "Tên ngành": "Kinh tế đầu tư",
          "Tổ hợp môn": "A00; A16; C01; D01",
          "Điểm chuẩn": "16",
          "Ghi chú": ""
        },
        {
          "Tên ngành": "Quan hệ quốc tế",
          "Tổ hợp môn": "C00; C15; D01; A01",
          "Điểm chuẩn": "16",
          "Ghi chú": ""
        },
        {
          "Tên ngành": "Việt Nam học",
          "Tổ hợp môn": "C00; C15; D01; A01",
          "Điểm chuẩn": "16",
          "Ghi chú": ""
        },
        {
          "Tên ngành": "Truyền thông đa phương tiện",
          "Tổ hợp môn": "C00; C15; D01; A00",
          "Điểm chuẩn": "16",
          "Ghi chú": ""
        },
        {
          "Tên ngành": "Quan hệ công chúng",
          "Tổ hợp môn": "C00; C15; D01; A01",
          "Điểm chuẩn": "16",
          "Ghi chú": ""
        },
        {
          "Tên ngành": "Quản trị kinh doanh",
          "Tổ hợp môn": "A00; A16; C01; D01",
          "Điểm chuẩn": "16",
          "Ghi chú": ""
        },
        {
          "Tên ngành": "Marketing",
          "Tổ hợp môn": "A00; A16; C01; D01",
          "Điểm chuẩn": "16",
          "Ghi chú": ""
        },
        {
          "Tên ngành": "Kinh doanh thương mại",
          "Tổ hợp môn": "A00; A16; C01; D01",
          "Điểm chuẩn": "16",
          "Ghi chú": ""
        },
        {
          "Tên ngành": "Thương mại điện tử",
          "Tổ hợp môn": "A00; A16; C01; D01",
          "Điểm chuẩn": "16",
          "Ghi chú": ""
        },
        {
          "Tên ngành": "Tài chính - Ngân hàng",
          "Tổ hợp môn": "A00; A16; C01; D01",
          "Điểm chuẩn": "16",
          "Ghi chú": ""
        },
        {
          "Tên ngành": "Kế toán",
          "Tổ hợp môn": "A00; A16; C01; D01",
          "Điểm chuẩn": "16",
          "Ghi chú": ""
        },
        {
          "Tên ngành": "Kiểm toán",
          "Tổ hợp môn": "A00; A16; C01; D01",
          "Điểm chuẩn": "16",
          "Ghi chú": ""
        },
        {
          "Tên ngành": "Quản trị nhân lực",
          "Tổ hợp môn": "A00; A16; C01; D01",
          "Điểm chuẩn": "16",
          "Ghi chú": ""
        },
        {
          "Tên ngành": "Hệ thống thông tin quản lý",
          "Tổ hợp môn": "A00; A16; A01; D01",
          "Điểm chuẩn": "16",
          "Ghi chú": ""
        },
        {
          "Tên ngành": "Quản trị sự kiện",
          "Tổ hợp môn": "A00; C00; C15; D01",
          "Điểm chuẩn": "16",
          "Ghi chú": ""
        },
        {
          "Tên ngành": "Luật",
          "Tổ hợp môn": "A00; C00; C15; D01",
          "Điểm chuẩn": "16",
          "Ghi chú": ""
        },
        {
          "Tên ngành": "Luật kinh tế",
          "Tổ hợp môn": "A00; C00; C15; D01",
          "Điểm chuẩn": "16",
          "Ghi chú": ""
        },
        {
          "Tên ngành": "Công nghệ sinh học",
          "Tổ hợp môn": "A00; A01; B00; B03",
          "Điểm chuẩn": "16",
          "Ghi chú": ""
        },
        {
          "Tên ngành": "Khoa học dữ liệu",
          "Tổ hợp môn": "A00; A16; A01; D01",
          "Điểm chuẩn": "16",
          "Ghi chú": ""
        },
        {
          "Tên ngành": "Khoa học máy tính",
          "Tổ hợp môn": "A00; A16; A01; D01",
          "Điểm chuẩn": "16",
          "Ghi chú": ""
        },
        {
          "Tên ngành": "Mạng Máy tính và Truyền thông Dữ liệu",
          "Tổ hợp môn": "A00; A16; A01; D01",
          "Điểm chuẩn": "16",
          "Ghi chú": ""
        },
        {
          "Tên ngành": "Kỹ thuật phần mềm",
          "Tổ hợp môn": "A00; A16; A01; D01",
          "Điểm chuẩn": "16",
          "Ghi chú": ""
        },
        {
          "Tên ngành": "Trí tuệ Nhân tạo",
          "Tổ hợp môn": "A00; A16; A01; D01",
          "Điểm chuẩn": "16",
          "Ghi chú": ""
        },
        {
          "Tên ngành": "An toàn Thông tin",
          "Tổ hợp môn": "A00; A16; A01; D01",
          "Điểm chuẩn": "16",
          "Ghi chú": ""
        },
        {
          "Tên ngành": "Công nghệ kỹ thuật Công trình xây dựng",
          "Tổ hợp môn": "A00; A16; C01; D01",
          "Điểm chuẩn": "16",
          "Ghi chú": ""
        },
        {
          "Tên ngành": "Công nghệ kỹ thuật ô tô",
          "Tổ hợp môn": "A00; A16; C01; D01",
          "Điểm chuẩn": "16",
          "Ghi chú": ""
        },
        {
          "Tên ngành": "Công nghệ Kỹ thuật điện, điện tử",
          "Tổ hợp môn": "A00; A16; C01; D01",
          "Điểm chuẩn": "16",
          "Ghi chú": ""
        },
        {
          "Tên ngành": "Công nghệ kỹ thuật môi trường",
          "Tổ hợp môn": "A00; A16; B00; C02",
          "Điểm chuẩn": "16",
          "Ghi chú": ""
        },
        {
          "Tên ngành": "Logistics và quản lý chuỗi cung ứng",
          "Tổ hợp môn": "A00; A16; C01; D01",
          "Điểm chuẩn": "16",
          "Ghi chú": ""
        },
        {
          "Tên ngành": "Kỹ thuật điện",
          "Tổ hợp môn": "A00; A16; C01; D01",
          "Điểm chuẩn": "16",
          "Ghi chú": ""
        },
        {
          "Tên ngành": "Kỹ thuật Y sinh",
          "Tổ hợp môn": "A00; A01; B00; B03",
          "Điểm chuẩn": "16",
          "Ghi chú": ""
        },
        {
          "Tên ngành": "Kỹ thuật Điện và Tự động hóa",
          "Tổ hợp môn": "A00; A16; C01; D01",
          "Điểm chuẩn": "16",
          "Ghi chú": ""
        },
        {
          "Tên ngành": "Công nghệ thực phẩm",
          "Tổ hợp môn": "A00; A01; B00; C01",
          "Điểm chuẩn": "16",
          "Ghi chú": ""
        },
        {
          "Tên ngành": "Kiến trúc",
          "Tổ hợp môn": "V00; V01; M02; M04",
          "Điểm chuẩn": "22",
          "Ghi chú": "Môn Vẽ nhân hệ số 2"
        },
        {
          "Tên ngành": "Kỹ thuật xây dựng",
          "Tổ hợp môn": "A00; A16; C01; D01",
          "Điểm chuẩn": "16",
          "Ghi chú": ""
        },
        {
          "Tên ngành": "Y khoa",
          "Tổ hợp môn": "A16; B00; D90; D08",
          "Điểm chuẩn": "22.5",
          "Ghi chú": ""
        },
        {
          "Tên ngành": "Dược",
          "Tổ hợp môn": "A00; A16; B00; B03",
          "Điểm chuẩn": "21",
          "Ghi chú": ""
        },
        {
          "Tên ngành": "Điều dưỡng",
          "Tổ hợp môn": "A00; A16; B00; B03",
          "Điểm chuẩn": "19",
          "Ghi chú": ""
        },
        {
          "Tên ngành": "Bác sĩ Răng Hàm Mặt",
          "Tổ hợp môn": "A00; A16; B00; D90",
          "Điểm chuẩn": "22.5",
          "Ghi chú": ""
        },
        {
          "Tên ngành": "Du lịch",
          "Tổ hợp môn": "A00; C00; C15; D01",
          "Điểm chuẩn": "16",
          "Ghi chú": ""
        },
        {
          "Tên ngành": "Quản trị dịch vụ du lịch và lữ hành",
          "Tổ hợp môn": "A00; C00; C15; D01",
          "Điểm chuẩn": "16",
          "Ghi chú": ""
        },
        {
          "Tên ngành": "Quản trị khách sạn",
          "Tổ hợp môn": "A00; C00; C15; D01",
          "Điểm chuẩn": "16",
          "Ghi chú": ""
        },
        {
          "Tên ngành": "Quản trị nhà hàng và Dịch vụ ăn uống",
          "Tổ hợp môn": "A00; C00; C15; D01",
          "Điểm chuẩn": "16",
          "Ghi chú": ""
        },
        {
          "Tên ngành": "Kinh tế gia đình",
          "Tổ hợp môn": "A00; C00; C15; D01",
          "Điểm chuẩn": "16",
          "Ghi chú": ""
        },
        {
          "Tên ngành": "Quản lý tài nguyên và môi trường",
          "Tổ hợp môn": "A00; A16; B00; C15",
          "Điểm chuẩn": "16",
          "Ghi chú": ""
        }
      ],
      "row_count": 52
    },
    {
      "table_title": "Điểm học bạ năm 2024",
      "headers": [
        "Tên ngành",
        "Tổ hợp môn",
        "Điểm chuẩn",
        "Ghi chú"
      ],
      "data": [
        {
          "Tên ngành": "Thiết kế đồ họa",
          "Tổ hợp môn": "A01; V01; C02; D01",
          "Điểm chuẩn": "18",
          "Ghi chú": ""
        },
        {
          "Tên ngành": "Thiết kế thời trang",
          "Tổ hợp môn": "A00; V01; C02; D01",
          "Điểm chuẩn": "18",
          "Ghi chú": ""
        },
        {
          "Tên ngành": "Ngôn ngữ Anh",
          "Tổ hợp môn": "D01; D14; D15; A01",
          "Điểm chuẩn": "18",
          "Ghi chú": ""
        },
        {
          "Tên ngành": "Ngôn ngữ Trung Quốc",
          "Tổ hợp môn": "D01; D14; D15; D09",
          "Điểm chuẩn": "18",
          "Ghi chú": ""
        },
        {
          "Tên ngành": "Ngôn ngữ Nhật",
          "Tổ hợp môn": "A01; D01; D14; D15",
          "Điểm chuẩn": "18",
          "Ghi chú": ""
        },
        {
          "Tên ngành": "Ngôn ngữ Hàn Quốc",
          "Tổ hợp môn": "D01; D13; D09; D10",
          "Điểm chuẩn": "18",
          "Ghi chú": ""
        },
        {
          "Tên ngành": "Văn học",
          "Tổ hợp môn": "C00; D01; C03; C04",
          "Điểm chuẩn": "18",
          "Ghi chú": ""
        },
        {
          "Tên ngành": "Kinh tế đầu tư",
          "Tổ hợp môn": "A00; C01; C02; D01",
          "Điểm chuẩn": "18",
          "Ghi chú": ""
        },
        {
          "Tên ngành": "Quan hệ quốc tế",
          "Tổ hợp môn": "C00; D01; C01; A01",
          "Điểm chuẩn": "18",
          "Ghi chú": ""
        },
        {
          "Tên ngành": "Việt Nam học",
          "Tổ hợp môn": "C00; D01; C01; A01",
          "Điểm chuẩn": "18",
          "Ghi chú": ""
        },
        {
          "Tên ngành": "Truyền thông đa phương tiện",
          "Tổ hợp môn": "C00; D01; A01; A00",
          "Điểm chuẩn": "18",
          "Ghi chú": ""
        },
        {
          "Tên ngành": "Quan hệ công chúng",
          "Tổ hợp môn": "C00; D01; C01; A01",
          "Điểm chuẩn": "18",
          "Ghi chú": ""
        },
        {
          "Tên ngành": "Quản trị kinh doanh",
          "Tổ hợp môn": "A00; C01; C02; D01",
          "Điểm chuẩn": "18",
          "Ghi chú": ""
        },
        {
          "Tên ngành": "Marketing",
          "Tổ hợp môn": "A00; C01; C02; D01",
          "Điểm chuẩn": "18",
          "Ghi chú": ""
        },
        {
          "Tên ngành": "Kinh doanh thương mại",
          "Tổ hợp môn": "A00; C01; C02; D01",
          "Điểm chuẩn": "18",
          "Ghi chú": ""
        },
        {
          "Tên ngành": "Thương mại điện tử",
          "Tổ hợp môn": "A00; C01; C02; D01",
          "Điểm chuẩn": "18",
          "Ghi chú": ""
        },
        {
          "Tên ngành": "Tài chính - Ngân hàng",
          "Tổ hợp môn": "A00; C01; C02; D01",
          "Điểm chuẩn": "18",
          "Ghi chú": ""
        },
        {
          "Tên ngành": "Kế toán",
          "Tổ hợp môn": "A00; C01; C02; D01",
          "Điểm chuẩn": "18",
          "Ghi chú": ""
        },
        {
          "Tên ngành": "Kiểm toán",
          "Tổ hợp môn": "A00; C01; C02; D01",
          "Điểm chuẩn": "18",
          "Ghi chú": ""
        },
        {
          "Tên ngành": "Quản trị nhân lực",
          "Tổ hợp môn": "A00; C01; C02; D01",
          "Điểm chuẩn": "18",
          "Ghi chú": ""
        },
        {
          "Tên ngành": "Hệ thống thông tin quản lý",
          "Tổ hợp môn": "A00; C01; C02; D01",
          "Điểm chuẩn": "18",
          "Ghi chú": "Ngành đạt kiểm định ABET-Hoa Kỳ"
        },
        {
          "Tên ngành": "Quản trị sự kiện",
          "Tổ hợp môn": "A00; A01; C00; D01",
          "Điểm chuẩn": "18",
          "Ghi chú": ""
        },
        {
          "Tên ngành": "Luật",
          "Tổ hợp môn": "A00; A01; C00; D01",
          "Điểm chuẩn": "18",
          "Ghi chú": ""
        },
        {
          "Tên ngành": "Luật kinh tế",
          "Tổ hợp môn": "A00; A01; C00; D01",
          "Điểm chuẩn": "18",
          "Ghi chú": ""
        },
        {
          "Tên ngành": "Công nghệ sinh học",
          "Tổ hợp môn": "A02; B00; B03; D08",
          "Điểm chuẩn": "18",
          "Ghi chú": ""
        },
        {
          "Tên ngành": "Khoa học dữ liệu",
          "Tổ hợp môn": "A00; C01; C02; D01",
          "Điểm chuẩn": "18",
          "Ghi chú": ""
        },
        {
          "Tên ngành": "Khoa học máy tinh",
          "Tổ hợp môn": "A00; C01; C02; D01",
          "Điểm chuẩn": "18",
          "Ghi chú": ""
        },
        {
          "Tên ngành": "Mạng Máy tính và Truyền thông Dữ liệu",
          "Tổ hợp môn": "A00; C01; C02; D01",
          "Điểm chuẩn": "18",
          "Ghi chú": ""
        },
        {
          "Tên ngành": "Kỹ thuật phần mềm*",
          "Tổ hợp môn": "A00; C01; C02; D01",
          "Điểm chuẩn": "18",
          "Ghi chú": "Ngành đạt kiểm định ABET-Hoa Kỳ"
        },
        {
          "Tên ngành": "Trí tuệ Nhân tạo",
          "Tổ hợp môn": "A00; C01; C02; D01",
          "Điểm chuẩn": "18",
          "Ghi chú": ""
        },
        {
          "Tên ngành": "An toàn Thông tin",
          "Tổ hợp môn": "A00; C01; C02; D01",
          "Điểm chuẩn": "18",
          "Ghi chú": ""
        },
        {
          "Tên ngành": "Công nghệ kỹ thuật Công trình xây dựng",
          "Tổ hợp môn": "A00; C01; C02; D01",
          "Điểm chuẩn": "18",
          "Ghi chú": ""
        },
        {
          "Tên ngành": "Công nghệ kỹ thuật ô tô",
          "Tổ hợp môn": "A00; C01; C02; D01",
          "Điểm chuẩn": "18",
          "Ghi chú": ""
        },
        {
          "Tên ngành": "Công nghệ Kỹ thuật điện, điện tử *",
          "Tổ hợp môn": "A00; C01; C02; D01",
          "Điểm chuẩn": "18",
          "Ghi chú": "Ngành đạt kiểm định ABET-Hoa Kỳ"
        },
        {
          "Tên ngành": "Công nghệ kỹ thuật môi trường",
          "Tổ hợp môn": "A00; C01; C02; B00",
          "Điểm chuẩn": "18",
          "Ghi chú": ""
        },
        {
          "Tên ngành": "Logistics và quản lý chuỗi cung ứng",
          "Tổ hợp môn": "A00; C01; C02; D01",
          "Điểm chuẩn": "18",
          "Ghi chú": ""
        },
        {
          "Tên ngành": "Kỹ thuật Y sinh",
          "Tổ hợp môn": "A00; B00; B03; C02",
          "Điểm chuẩn": "18",
          "Ghi chú": ""
        },
        {
          "Tên ngành": "Kỹ thuật Điều khiển và Tự động hóa",
          "Tổ hợp môn": "A00; C01; C02; D01",
          "Điểm chuẩn": "18",
          "Ghi chú": ""
        },
        {
          "Tên ngành": "Công nghệ thực phẩm",
          "Tổ hợp môn": "A00; C01; C02; B00",
          "Điểm chuẩn": "18",
          "Ghi chú": ""
        },
        {
          "Tên ngành": "Kiến trúc",
          "Tổ hợp môn": "V00; V01; V02; V06",
          "Điểm chuẩn": "20",
          "Ghi chú": "Điểm vẽ nhân hệ số 2"
        },
        {
          "Tên ngành": "Kỹ thuật xây dựng",
          "Tổ hợp môn": "A00; C01; C02; D01",
          "Điểm chuẩn": "18",
          "Ghi chú": ""
        },
        {
          "Tên ngành": "Dược",
          "Tổ hợp môn": "A00; B00; B03; C02",
          "Điểm chuẩn": "24",
          "Ghi chú": "HL lớp 12 Giỏi hoặc điểm xét tốt nghiệp THPT từ 8.0 trở lên"
        },
        {
          "Tên ngành": "Y khoa",
          "Tổ hợp môn": "A00; B00; A02; D08",
          "Điểm chuẩn": "24",
          "Ghi chú": "HL lớp 12 Giỏi hoặc điểm xét tốt nghiệp THPT từ 8.0 trở lên"
        },
        {
          "Tên ngành": "Điều dưỡng",
          "Tổ hợp môn": "A00; B00; B03; C02",
          "Điểm chuẩn": "19.5",
          "Ghi chú": "HL lớp 12 Khá hoặc điểm xét tốt nghiệp THPT từ 6.5 trở lên"
        },
        {
          "Tên ngành": "Bác sĩ Răng Hàm Mặt",
          "Tổ hợp môn": "A00; B00; A02; D08",
          "Điểm chuẩn": "24",
          "Ghi chú": "HL lớp 12 Giỏi hoặc điểm xét tốt nghiệp THPT từ 8.0 trở lên"
        },
        {
          "Tên ngành": "Du lịch",
          "Tổ hợp môn": "A00; A01; C00; D01",
          "Điểm chuẩn": "18",
          "Ghi chú": ""
        },
        {
          "Tên ngành": "Quản trị dịch vụ du lịch và lữ hành",
          "Tổ hợp môn": "A00; A01; C00; D01",
          "Điểm chuẩn": "18",
          "Ghi chú": ""
        },
        {
          "Tên ngành": "Quản trị khách sạn",
          "Tổ hợp môn": "A00; A01; C00; D01",
          "Điểm chuẩn": "18",
          "Ghi chú": "Ngành đạt kiểm định UNWTO"
        },
        {
          "Tên ngành": "Quản trị nhà hàng và Dịch vụ ăn uống",
          "Tổ hợp môn": "A00; A01; C00; D01",
          "Điểm chuẩn": "18",
          "Ghi chú": ""
        },
        {
          "Tên ngành": "Kinh tế gia đình",
          "Tổ hợp môn": "A00; A01; C00; D01",
          "Điểm chuẩn": "18",
          "Ghi chú": ""
        },
        {
          "Tên ngành": "Quản lý tài nguyên và môi trường",
          "Tổ hợp môn": "A00; C01; C02; B00",
          "Điểm chuẩn": "18",
          "Ghi chú": ""
        }
      ],
      "row_count": 51
    },
    {
      "table_title": "Điểm ĐGNL HN năm 2024",
      "headers": [
        "Tên ngành",
        "Tổ hợp môn",
        "Điểm chuẩn",
        "Ghi chú"
      ],
      "data": [
        {
          "Tên ngành": "Thiết kế đồ họa",
          "Tổ hợp môn": "",
          "Điểm chuẩn": "85",
          "Ghi chú": ""
        },
        {
          "Tên ngành": "Thiết kế thời trang",
          "Tổ hợp môn": "",
          "Điểm chuẩn": "85",
          "Ghi chú": ""
        },
        {
          "Tên ngành": "Ngôn ngữ Anh",
          "Tổ hợp môn": "",
          "Điểm chuẩn": "85",
          "Ghi chú": ""
        },
        {
          "Tên ngành": "Ngôn ngữ Trung Quốc",
          "Tổ hợp môn": "",
          "Điểm chuẩn": "85",
          "Ghi chú": ""
        },
        {
          "Tên ngành": "Ngôn ngữ Nhật",
          "Tổ hợp môn": "",
          "Điểm chuẩn": "85",
          "Ghi chú": ""
        },
        {
          "Tên ngành": "Ngôn ngữ Hàn Quốc",
          "Tổ hợp môn": "",
          "Điểm chuẩn": "85",
          "Ghi chú": ""
        },
        {
          "Tên ngành": "Văn học",
          "Tổ hợp môn": "",
          "Điểm chuẩn": "85",
          "Ghi chú": ""
        },
        {
          "Tên ngành": "Kinh tế đầu tư",
          "Tổ hợp môn": "",
          "Điểm chuẩn": "85",
          "Ghi chú": ""
        },
        {
          "Tên ngành": "Quan hệ quốc tế",
          "Tổ hợp môn": "",
          "Điểm chuẩn": "85",
          "Ghi chú": ""
        },
        {
          "Tên ngành": "Việt Nam học",
          "Tổ hợp môn": "",
          "Điểm chuẩn": "85",
          "Ghi chú": ""
        },
        {
          "Tên ngành": "Truyền thông đa phương tiện",
          "Tổ hợp môn": "",
          "Điểm chuẩn": "85",
          "Ghi chú": ""
        },
        {
          "Tên ngành": "Quan hệ công chúng",
          "Tổ hợp môn": "",
          "Điểm chuẩn": "85",
          "Ghi chú": ""
        },
        {
          "Tên ngành": "Quản trị kinh doanh",
          "Tổ hợp môn": "",
          "Điểm chuẩn": "85",
          "Ghi chú": ""
        },
        {
          "Tên ngành": "Marketing",
          "Tổ hợp môn": "",
          "Điểm chuẩn": "85",
          "Ghi chú": ""
        },
        {
          "Tên ngành": "Kinh doanh thương mại",
          "Tổ hợp môn": "",
          "Điểm chuẩn": "85",
          "Ghi chú": ""
        },
        {
          "Tên ngành": "Thương mại điện tử",
          "Tổ hợp môn": "",
          "Điểm chuẩn": "85",
          "Ghi chú": ""
        },
        {
          "Tên ngành": "Tài chính - Ngân hàng",
          "Tổ hợp môn": "",
          "Điểm chuẩn": "85",
          "Ghi chú": ""
        },
        {
          "Tên ngành": "Kế toán",
          "Tổ hợp môn": "",
          "Điểm chuẩn": "85",
          "Ghi chú": ""
        },
        {
          "Tên ngành": "Kiểm toán",
          "Tổ hợp môn": "",
          "Điểm chuẩn": "85",
          "Ghi chú": ""
        },
        {
          "Tên ngành": "Quản trị nhân lực",
          "Tổ hợp môn": "",
          "Điểm chuẩn": "85",
          "Ghi chú": ""
        },
        {
          "Tên ngành": "Hệ thống thông tin quản lý",
          "Tổ hợp môn": "",
          "Điểm chuẩn": "85",
          "Ghi chú": "Ngành đạt kiểm định ABET-Hoa Kỳ"
        },
        {
          "Tên ngành": "Quản trị sự kiện",
          "Tổ hợp môn": "",
          "Điểm chuẩn": "85",
          "Ghi chú": ""
        },
        {
          "Tên ngành": "Luật",
          "Tổ hợp môn": "",
          "Điểm chuẩn": "85",
          "Ghi chú": ""
        },
        {
          "Tên ngành": "Luật kinh tế",
          "Tổ hợp môn": "",
          "Điểm chuẩn": "85",
          "Ghi chú": ""
        },
        {
          "Tên ngành": "Công nghệ sinh học",
          "Tổ hợp môn": "",
          "Điểm chuẩn": "85",
          "Ghi chú": ""
        },
        {
          "Tên ngành": "Khoa học dữ liệu",
          "Tổ hợp môn": "",
          "Điểm chuẩn": "85",
          "Ghi chú": ""
        },
        {
          "Tên ngành": "Khoa học máy tinh",
          "Tổ hợp môn": "",
          "Điểm chuẩn": "85",
          "Ghi chú": ""
        },
        {
          "Tên ngành": "Mạng Máy tính và Truyền thông Dữ liệu",
          "Tổ hợp môn": "",
          "Điểm chuẩn": "85",
          "Ghi chú": ""
        },
        {
          "Tên ngành": "Kỹ thuật phần mềm",
          "Tổ hợp môn": "",
          "Điểm chuẩn": "85",
          "Ghi chú": "Ngành đạt kiểm định ABET-Hoa Kỳ"
        },
        {
          "Tên ngành": "Trí tuệ Nhân tạo",
          "Tổ hợp môn": "",
          "Điểm chuẩn": "85",
          "Ghi chú": ""
        },
        {
          "Tên ngành": "An toàn Thông tin",
          "Tổ hợp môn": "",
          "Điểm chuẩn": "85",
          "Ghi chú": ""
        },
        {
          "Tên ngành": "Công nghệ kỹ thuật Công trình xây dựng",
          "Tổ hợp môn": "",
          "Điểm chuẩn": "85",
          "Ghi chú": ""
        },
        {
          "Tên ngành": "Công nghệ kỹ thuật ô tô",
          "Tổ hợp môn": "",
          "Điểm chuẩn": "85",
          "Ghi chú": ""
        },
        {
          "Tên ngành": "Công nghệ Kỹ thuật điện, điện tử",
          "Tổ hợp môn": "",
          "Điểm chuẩn": "85",
          "Ghi chú": "Ngành đạt kiểm định ABET-Hoa Kỳ"
        },
        {
          "Tên ngành": "Công nghệ kỹ thuật môi trường",
          "Tổ hợp môn": "",
          "Điểm chuẩn": "85",
          "Ghi chú": ""
        },
        {
          "Tên ngành": "Logistics và quản lý chuỗi cung ứng",
          "Tổ hợp môn": "",
          "Điểm chuẩn": "85",
          "Ghi chú": ""
        },
        {
          "Tên ngành": "Kỹ thuật Y sinh",
          "Tổ hợp môn": "",
          "Điểm chuẩn": "85",
          "Ghi chú": ""
        },
        {
          "Tên ngành": "Kỹ thuật Điều khiển và Tự động hóa",
          "Tổ hợp môn": "",
          "Điểm chuẩn": "85",
          "Ghi chú": ""
        },
        {
          "Tên ngành": "Công nghệ thực phẩm",
          "Tổ hợp môn": "",
          "Điểm chuẩn": "85",
          "Ghi chú": ""
        },
        {
          "Tên ngành": "Kiến trúc",
          "Tổ hợp môn": "",
          "Điểm chuẩn": "85",
          "Ghi chú": ""
        },
        {
          "Tên ngành": "Kỹ thuật xây dựng",
          "Tổ hợp môn": "",
          "Điểm chuẩn": "85",
          "Ghi chú": ""
        },
        {
          "Tên ngành": "Y khoa",
          "Tổ hợp môn": "",
          "Điểm chuẩn": "100",
          "Ghi chú": "HL lớp 12 Giỏi hoặc điểm xét tốt nghiệp THPT từ 8.0 trở lên"
        },
        {
          "Tên ngành": "Dược",
          "Tổ hợp môn": "",
          "Điểm chuẩn": "100",
          "Ghi chú": "HL lớp 12 Giỏi hoặc điểm xét tốt nghiệp THPT từ 8.0 trở lên"
        },
        {
          "Tên ngành": "Điều dưỡng",
          "Tổ hợp môn": "",
          "Điểm chuẩn": "90",
          "Ghi chú": "HL lớp 12 Khá hoặc điểm xét tốt nghiệp THPT từ 6.5 trở lên"
        },
        {
          "Tên ngành": "Bác sĩ Răng Hàm Mặt",
          "Tổ hợp môn": "",
          "Điểm chuẩn": "100",
          "Ghi chú": "HL lớp 12 Giỏi hoặc điểm xét tốt nghiệp THPT từ 8.0 trở lên"
        },
        {
          "Tên ngành": "Du lịch",
          "Tổ hợp môn": "",
          "Điểm chuẩn": "85",
          "Ghi chú": ""
        },
        {
          "Tên ngành": "Quản trị dịch vụ du lịch và lữ hành",
          "Tổ hợp môn": "",
          "Điểm chuẩn": "85",
          "Ghi chú": ""
        },
        {
          "Tên ngành": "Quản trị khách sạn",
          "Tổ hợp môn": "",
          "Điểm chuẩn": "85",
          "Ghi chú": "Ngành đạt kiểm định UNWTO"
        },
        {
          "Tên ngành": "Quản trị nhà hàng và Dịch vụ ăn uống",
          "Tổ hợp môn": "",
          "Điểm chuẩn": "85",
          "Ghi chú": ""
        },
        {
          "Tên ngành": "Kinh tế gia đình",
          "Tổ hợp môn": "",
          "Điểm chuẩn": "85",
          "Ghi chú": ""
        },
        {
          "Tên ngành": "Quản lý tài nguyên và môi trường",
          "Tổ hợp môn": "",
          "Điểm chuẩn": "85",
          "Ghi chú": ""
        }
      ],
      "row_count": 51
    },
    {
      "table_title": "Điểm ĐGNL HCM năm 2024",
      "headers": [
        "Tên ngành",
        "Tổ hợp môn",
        "Điểm chuẩn",
        "Ghi chú"
      ],
      "data": [
        {
          "Tên ngành": "Thiết kế đồ họa",
          "Tổ hợp môn": "",
          "Điểm chuẩn": "650",
          "Ghi chú": ""
        },
        {
          "Tên ngành": "Thiết kế thời trang",
          "Tổ hợp môn": "",
          "Điểm chuẩn": "650",
          "Ghi chú": ""
        },
        {
          "Tên ngành": "Ngôn ngữ Anh",
          "Tổ hợp môn": "",
          "Điểm chuẩn": "650",
          "Ghi chú": ""
        },
        {
          "Tên ngành": "Ngôn ngữ Trung Quốc",
          "Tổ hợp môn": "",
          "Điểm chuẩn": "650",
          "Ghi chú": ""
        },
        {
          "Tên ngành": "Ngôn ngữ Nhật",
          "Tổ hợp môn": "",
          "Điểm chuẩn": "650",
          "Ghi chú": ""
        },
        {
          "Tên ngành": "Ngôn ngữ Hàn Quốc",
          "Tổ hợp môn": "",
          "Điểm chuẩn": "650",
          "Ghi chú": ""
        },
        {
          "Tên ngành": "Văn học",
          "Tổ hợp môn": "",
          "Điểm chuẩn": "650",
          "Ghi chú": ""
        },
        {
          "Tên ngành": "Kinh tế đầu tư",
          "Tổ hợp môn": "",
          "Điểm chuẩn": "650",
          "Ghi chú": ""
        },
        {
          "Tên ngành": "Quan hệ quốc tế",
          "Tổ hợp môn": "",
          "Điểm chuẩn": "650",
          "Ghi chú": ""
        },
        {
          "Tên ngành": "Việt Nam học",
          "Tổ hợp môn": "",
          "Điểm chuẩn": "650",
          "Ghi chú": ""
        },
        {
          "Tên ngành": "Truyền thông đa phương tiện",
          "Tổ hợp môn": "",
          "Điểm chuẩn": "650",
          "Ghi chú": ""
        },
        {
          "Tên ngành": "Quan hệ công chúng",
          "Tổ hợp môn": "",
          "Điểm chuẩn": "650",
          "Ghi chú": ""
        },
        {
          "Tên ngành": "Quản trị kinh doanh",
          "Tổ hợp môn": "",
          "Điểm chuẩn": "650",
          "Ghi chú": ""
        },
        {
          "Tên ngành": "Marketing",
          "Tổ hợp môn": "",
          "Điểm chuẩn": "650",
          "Ghi chú": ""
        },
        {
          "Tên ngành": "Kinh doanh thương mại",
          "Tổ hợp môn": "",
          "Điểm chuẩn": "650",
          "Ghi chú": ""
        },
        {
          "Tên ngành": "Thương mại điện tử",
          "Tổ hợp môn": "",
          "Điểm chuẩn": "650",
          "Ghi chú": ""
        },
        {
          "Tên ngành": "Tài chính - Ngân hàng",
          "Tổ hợp môn": "",
          "Điểm chuẩn": "650",
          "Ghi chú": ""
        },
        {
          "Tên ngành": "Kế toán",
          "Tổ hợp môn": "",
          "Điểm chuẩn": "650",
          "Ghi chú": ""
        },
        {
          "Tên ngành": "Kiểm toán",
          "Tổ hợp môn": "",
          "Điểm chuẩn": "650",
          "Ghi chú": ""
        },
        {
          "Tên ngành": "Quản trị nhân lực",
          "Tổ hợp môn": "",
          "Điểm chuẩn": "650",
          "Ghi chú": ""
        },
        {
          "Tên ngành": "Hệ thống thông tin quản lý",
          "Tổ hợp môn": "",
          "Điểm chuẩn": "650",
          "Ghi chú": "Ngành đạt kiểm định ABET-Hoa Kỳ"
        },
        {
          "Tên ngành": "Quản trị sự kiện",
          "Tổ hợp môn": "",
          "Điểm chuẩn": "650",
          "Ghi chú": ""
        },
        {
          "Tên ngành": "Luật",
          "Tổ hợp môn": "",
          "Điểm chuẩn": "650",
          "Ghi chú": ""
        },
        {
          "Tên ngành": "Luật kinh tế",
          "Tổ hợp môn": "",
          "Điểm chuẩn": "650",
          "Ghi chú": ""
        },
        {
          "Tên ngành": "Công nghệ sinh học",
          "Tổ hợp môn": "",
          "Điểm chuẩn": "650",
          "Ghi chú": ""
        },
        {
          "Tên ngành": "Khoa học dữ liệu",
          "Tổ hợp môn": "",
          "Điểm chuẩn": "650",
          "Ghi chú": ""
        },
        {
          "Tên ngành": "Khoa học máy tinh",
          "Tổ hợp môn": "",
          "Điểm chuẩn": "650",
          "Ghi chú": ""
        },
        {
          "Tên ngành": "Mạng Máy tính và Truyền thông Dữ liệu",
          "Tổ hợp môn": "",
          "Điểm chuẩn": "650",
          "Ghi chú": ""
        },
        {
          "Tên ngành": "Kỹ thuật phần mềm",
          "Tổ hợp môn": "",
          "Điểm chuẩn": "650",
          "Ghi chú": "Ngành đạt kiểm định ABET-Hoa Kỳ"
        },
        {
          "Tên ngành": "Trí tuệ Nhân tạo",
          "Tổ hợp môn": "",
          "Điểm chuẩn": "650",
          "Ghi chú": ""
        },
        {
          "Tên ngành": "An toàn Thông tin",
          "Tổ hợp môn": "",
          "Điểm chuẩn": "650",
          "Ghi chú": ""
        },
        {
          "Tên ngành": "Công nghệ kỹ thuật Công trình xây dựng",
          "Tổ hợp môn": "",
          "Điểm chuẩn": "650",
          "Ghi chú": ""
        },
        {
          "Tên ngành": "Công nghệ kỹ thuật ô tổ",
          "Tổ hợp môn": "",
          "Điểm chuẩn": "650",
          "Ghi chú": ""
        },
        {
          "Tên ngành": "Công nghệ Kỹ thuật điện, điện tử",
          "Tổ hợp môn": "",
          "Điểm chuẩn": "650",
          "Ghi chú": "Ngành đạt kiểm định ABET-Hoa Kỳ"
        },
        {
          "Tên ngành": "Công nghệ kỹ thuật môi trường",
          "Tổ hợp môn": "",
          "Điểm chuẩn": "650",
          "Ghi chú": ""
        },
        {
          "Tên ngành": "Logistics và quản lý chuỗi cung ứng",
          "Tổ hợp môn": "",
          "Điểm chuẩn": "650",
          "Ghi chú": ""
        },
        {
          "Tên ngành": "Kỹ thuật Y sinh",
          "Tổ hợp môn": "",
          "Điểm chuẩn": "650",
          "Ghi chú": ""
        },
        {
          "Tên ngành": "Kỹ thuật Điều khiển và Tự động hóa",
          "Tổ hợp môn": "",
          "Điểm chuẩn": "650",
          "Ghi chú": ""
        },
        {
          "Tên ngành": "Công nghệ thực phẩm",
          "Tổ hợp môn": "",
          "Điểm chuẩn": "650",
          "Ghi chú": ""
        },
        {
          "Tên ngành": "Kiến trúc",
          "Tổ hợp môn": "",
          "Điểm chuẩn": "650",
          "Ghi chú": ""
        },
        {
          "Tên ngành": "Kỹ thuật xây dựng",
          "Tổ hợp môn": "",
          "Điểm chuẩn": "650",
          "Ghi chú": ""
        },
        {
          "Tên ngành": "Dược",
          "Tổ hợp môn": "",
          "Điểm chuẩn": "750",
          "Ghi chú": "HL lớp 12 Giỏi hoặc điểm xét tốt nghiệp THPT từ 8.0 trở lên"
        },
        {
          "Tên ngành": "Y khoa",
          "Tổ hợp môn": "",
          "Điểm chuẩn": "750",
          "Ghi chú": "HL lớp 12 Giỏi hoặc điểm xét tốt nghiệp THPT từ 8.0 trở lên"
        },
        {
          "Tên ngành": "Điều dưỡng",
          "Tổ hợp môn": "",
          "Điểm chuẩn": "700",
          "Ghi chú": "HL lớp 12 Khá hoặc điểm xét tốt nghiệp THPT từ 6.5 trở lên"
        },
        {
          "Tên ngành": "Bác sĩ Răng Hàm Mặt",
          "Tổ hợp môn": "",
          "Điểm chuẩn": "750",
          "Ghi chú": "HL lớp 12 Giỏi hoặc điểm xét tốt nghiệp THPT từ 8.0 trở lên"
        },
        {
          "Tên ngành": "Du lịch",
          "Tổ hợp môn": "",
          "Điểm chuẩn": "650",
          "Ghi chú": ""
        },
        {
          "Tên ngành": "Quản trị dịch vụ du lịch và lữ hành",
          "Tổ hợp môn": "",
          "Điểm chuẩn": "650",
          "Ghi chú": ""
        },
        {
          "Tên ngành": "Quản trị khách sạn",
          "Tổ hợp môn": "",
          "Điểm chuẩn": "650",
          "Ghi chú": "Ngành đạt kiểm định UNWTO"
        },
        {
          "Tên ngành": "Quản trị nhà hàng và Dịch vụ ăn uống",
          "Tổ hợp môn": "",
          "Điểm chuẩn": "650",
          "Ghi chú": ""
        },
        {
          "Tên ngành": "Kinh tế gia đình",
          "Tổ hợp môn": "",
          "Điểm chuẩn": "650",
          "Ghi chú": ""
        },
        {
          "Tên ngành": "Quản lý tài nguyên và môi trường",
          "Tổ hợp môn": "",
          "Điểm chuẩn": "650",
          "Ghi chú": ""
        }
      ],
      "row_count": 51
    }
  ],
  "table_count": 4,
  "crawled_at": "2025-07-18T23:28:15.655504",
  "source_url": "https://diemthi.tuyensinh247.com/diem-chuan/dai-hoc-duy-tan-DDT.html"
}